django_firebase_auth/__init__.py
django_firebase_auth/apps.py
django_firebase_auth/auth/__init__.py
django_firebase_auth/auth/middleware.py
django_firebase_auth/base.py
django_firebase_auth/migrations/0001_initial.py
django_firebase_auth/migrations/__init__.py
django_firebase_auth/models.py
django_firebase_auth_sdk-0.1.5.dist-info/LICENSE
django_firebase_auth_sdk-0.1.5.dist-info/METADATA
django_firebase_auth_sdk-0.1.5.dist-info/WHEEL
django_firebase_auth_sdk-0.1.5.dist-info/RECORD
