Metadata-Version: 2.3
Name: django-firebase-auth-sdk
Version: 0.1.5
Summary: Django 사용자 인증을 위한 Firebase 통합
Author: 94wogus
Author-email: 94wogus@gmail.com
Requires-Python: >=3.12,<4.0
Classifier: Programming Language :: Python :: 3
Classifier: Programming Language :: Python :: 3.12
Classifier: Programming Language :: Python :: 3.13
Requires-Dist: django (>=5.1,<6.0)
Requires-Dist: djangorestframework (>=3.15,<3.16)
Requires-Dist: firebase-admin (>=6.3,<7.0)
Requires-Dist: graphql-core (>=3.1,<3.3)
